emailpysender/__init__.py
emailpysender/email_utils.py
emailpysender-0.0.2.dist-info/DESCRIPTION.rst
emailpysender-0.0.2.dist-info/METADATA
emailpysender-0.0.2.dist-info/RECORD
emailpysender-0.0.2.dist-info/WHEEL
emailpysender-0.0.2.dist-info/metadata.json
emailpysender-0.0.2.dist-info/top_level.txt
