Metadata-Version: 2.0
Name: emailpysender
Version: 0.0.2
Summary: Small library for sending html emails with attachments
Home-page: https://github.com/serbernar/emailpysender
Author: 53r63rn4r
Author-email: serbernar1@gmail.com
License: MIT
Download-URL: https://github.com/serbernar/emailpysender/archive/master.zip
Platform: UNKNOWN
Classifier: License :: OSI Approved :: MIT License
Classifier: Programming Language :: Python :: 3.4
Classifier: Programming Language :: Python :: 3.5
Requires-Dist: premailer
Requires-Dist: ujson
